folderbot/__init__.py
folderbot/__main__.py
folderbot/claude_client.py
folderbot/cli.py
folderbot/config.example.yaml
folderbot/config.py
folderbot/context_builder.py
folderbot/file_watcher.py
folderbot/migration.py
folderbot/session_manager.py
folderbot/telegram_handler.py
folderbot/prompts/__init__.py
folderbot/prompts/action_validator.txt
folderbot/prompts/system.txt
folderbot/prompts/task_summary.txt
folderbot/prompts/tool_retry_correction.txt
folderbot/scheduler/__init__.py
folderbot/scheduler/models.py
folderbot/scheduler/persistence.py
folderbot/scheduler/scheduler.py
folderbot/scheduler/tools.py
folderbot/tools/__init__.py
folderbot/tools/activity_log.py
folderbot/tools/base.py
folderbot/tools/file_notifications.py
folderbot/tools/folder_tools.py
folderbot/tools/helpers.py
folderbot/tools/list_files.py
folderbot/tools/loader.py
folderbot/tools/read_file.py
folderbot/tools/read_files.py
folderbot/tools/search_files.py
folderbot/tools/utils.py
folderbot/tools/web_fetch.py
folderbot/tools/web_search.py
folderbot/tools/web_tools.py
folderbot/tools/write_file.py
folderbot-0.1.28.dist-info/METADATA
folderbot-0.1.28.dist-info/WHEEL
folderbot-0.1.28.dist-info/entry_points.txt
folderbot-0.1.28.dist-info/RECORD
