Metadata-Version: 2.4
Name: folderbot
Version: 0.1.28
Summary: Telegram bot for chatting with your folder using Claude AI
Project-URL: Homepage, https://gitlab.com/jorgeecardona/folderbot
Project-URL: Repository, https://gitlab.com/jorgeecardona/folderbot
Author: Jorge Cardona
License-Expression: MIT
Keywords: ai,bot,claude,personal-assistant,telegram
Classifier: Development Status :: 3 - Alpha
Classifier: Intended Audience :: End Users/Desktop
Classifier: License :: OSI Approved :: MIT License
Classifier: Programming Language :: Python :: 3
Classifier: Programming Language :: Python :: 3.11
Classifier: Programming Language :: Python :: 3.12
Classifier: Programming Language :: Python :: 3.13
Requires-Python: >=3.11
Requires-Dist: anthropic>=0.70.0
Requires-Dist: beautifulsoup4>=4.12
Requires-Dist: croniter>=5.0
Requires-Dist: duckduckgo-search>=6.0
Requires-Dist: httpx>=0.27
Requires-Dist: pathspec>=0.12.0
Requires-Dist: pydantic>=2.0
Requires-Dist: python-dotenv>=1.0
Requires-Dist: python-telegram-bot>=22.0
Requires-Dist: pyyaml>=6.0
Requires-Dist: watchdog>=4.0
Provides-Extra: dev
Requires-Dist: pytest-asyncio>=1.3; extra == 'dev'
Requires-Dist: pytest-cov>=7.0; extra == 'dev'
Requires-Dist: pytest>=9.0; extra == 'dev'
